cointraderkr.py
api/__init__.py
api/asgi.py
api/settings.py
api/urls.py
api/wsgi.py
clients/__init__.py
clients/docker_client.py
clients/log_client.py
collectors/__init__.py
collectors/metric_collector.py
db/__init__.py
db/admin.py
db/apps.py
db/handler.py
db/models.py
db/serializers.py
db/urls.py
db/views.py
db/migrations/0001_initial.py
db/migrations/0002_auto_20210823_2108.py
db/migrations/0003_accesstoken.py
db/migrations/__init__.py
fastapi_utils/__init__.py
fastapi_utils/api_streamers.py
fastapi_utils/db.py
fastapi_utils/manager.py
fastapi_utils/templates.py
loaders/__init__.py
loaders/ftp_loader.py
loaders/loader.py
loaders/nas_loader.py
source/__init__.py
source/api.py
source/binance_api/__init__.py
source/binance_api/make_min_trader_amount.py
source/binance_api/meta.py
source/binance_api/min_trade_amount.pkl
source/binance_api/restapi.py
source/binance_api/ws.py
source/binance_api/ws_v2.py
source/binance_api/__pycache__/__init__.cpython-38.pyc
source/binance_api/__pycache__/restapi.cpython-38.pyc
source/bybit_api/__init__.py
source/bybit_api/restapi.py
source/bybit_api/ws.py
source/upbit_api/__init__.py
source/upbit_api/restapi.py
source/upbit_api/ws.py
streamers/__init__.py
streamers/data_streamer.py
streamers/log_streamer.py
streamers/metric_streamer.py
tests/__init__.py
tests/django/__init__.py
tests/django/test_db_api.py
tests/django/test_db_handler.py
tests/django/test_db_models.py
tests/fastapi/__init__.py
tests/fastapi/test_main_restapi.py
tests/fastapi/test_main_websocket.py
tests/influxdb/__init__.py
tests/influxdb/test_metric_collector.py
tests/influxdb/test_metric_streamer.py
tests/source/__init__.py
tests/source/test_binance_api.py
tests/source/test_binance_ws.py
tests/source/test_bybit_api.py
tests/source/test_bybit_ws.py
cointraderkr-0.2.0.dist-info/METADATA
cointraderkr-0.2.0.dist-info/WHEEL
cointraderkr-0.2.0.dist-info/top_level.txt
cointraderkr-0.2.0.dist-info/RECORD
