Metadata-Version: 2.1
Name: cointraderkr
Version: 0.2.0
Summary: Coin Trader API
Home-page: UNKNOWN
Author: Phillip Park
Author-email: ppark9553@gmail.com
License: UNKNOWN
Platform: UNKNOWN
Requires-Dist: python-dotenv
Requires-Dist: python-binance (==0.7.9)
Requires-Dist: Bybit (==0.2.12)
Requires-Dist: influxdb-client
Requires-Dist: paramiko
Requires-Dist: pandas
Requires-Dist: websocket-client (==0.53.0)
Requires-Dist: jwt
Requires-Dist: requests
Requires-Dist: pytz
